pycfgcut-0.3.2.dist-info/METADATA
pycfgcut-0.3.2.dist-info/WHEEL
pycfgcut-0.3.2.dist-info/licenses/LICENSE
pycfgcut/__init__.py
pycfgcut/pycfgcut.pyd
pycfgcut-0.3.2.dist-info/RECORD
