Metadata-Version: 2.4
Name: pycfgcut
Version: 0.3.2
Classifier: Development Status :: 5 - Production/Stable
Classifier: Intended Audience :: System Administrators
Classifier: Intended Audience :: Telecommunications Industry
Classifier: License :: OSI Approved :: MIT License
Classifier: Operating System :: MacOS :: MacOS X
Classifier: Operating System :: POSIX :: Linux
Classifier: Programming Language :: Python :: 3 :: Only
Classifier: Programming Language :: Python :: 3.9
Classifier: Programming Language :: Python :: 3.10
Classifier: Programming Language :: Python :: 3.11
Classifier: Programming Language :: Python :: 3.12
Classifier: Programming Language :: Python :: 3.13
Classifier: Programming Language :: Python :: 3.14
Classifier: Programming Language :: Rust
Classifier: Topic :: System :: Networking
Classifier: Topic :: Software Development :: Libraries
License-File: LICENSE
Summary: Python bindings for cfgcut, the deterministic configuration slicer
Keywords: cfgcut,networking,automation
Home-Page: https://cfgcut.bedecarroll.com
Author: cfgcut maintainers
Requires-Python: >=3.9
Project-URL: Homepage, https://cfgcut.bedecarroll.com
Project-URL: Documentation, https://cfgcut.bedecarroll.com
Project-URL: Repository, https://github.com/bedecarroll/cfgcut
Project-URL: Changelog, https://github.com/bedecarroll/cfgcut/blob/main/CHANGELOG.md
